{
	"description": "项目配置文件",
	"packOptions": {
		"ignore": []
	},
	"setting": {
		"urlCheck": true,
		"es6": true,
		"enhance": false,
		"postcss": true,
		"preloadBackgroundData": false,
		"minified": true,
		"newFeature": false,
		"coverView": true,
		"nodeModules": true,
		"autoAudits": false,
		"showShadowRootInWxmlPanel": true,
		"scopeDataCheck": false,
		"uglifyFileName": false,
		"checkInvalidKey": true,
		"checkSiteMap": false,
		"uploadWithSourceMap": true,
		"compileHotReLoad": false,
		"babelSetting": {
			"ignore": [],
			"disablePlugins": [],
			"outputPath": ""
		},
		"useIsolateContext": true,
		"useCompilerModule": false,
		"userConfirmedUseCompilerModuleSwitch": false
	},
	"compileType": "miniprogram",
	"libVersion": "2.12.0",
	"appid": "wx66ba0a4458bbf991",
	"projectname": "%E5%91%8A%E5%A4%A9%E4%B8%8B",
	"debugOptions": {
		"hidedInDevtools": []
	},
	"scripts": {},
	"isGameTourist": false,
	"simulatorType": "wechat",
	"simulatorPluginLibVersion": {},
	"condition": {
		"search": {
			"current": -1,
			"list": []
		},
		"conversation": {
			"current": -1,
			"list": []
		},
		"plugin": {
			"current": -1,
			"list": []
		},
		"game": {
			"current": -1,
			"list": []
		},
		"gamePlugin": {
			"current": -1,
			"list": []
		},
		"miniprogram": {
			"current": -1,
			"list": [
				{
					"id": -1,
					"name": "pages/classify/classify",
					"pathName": "pages/classify/classify",
					"query": "",
					"scene": null
				},
				{
					"id": -1,
					"name": "pages/mine/mine",
					"pathName": "pages/mine/mine",
					"query": "",
					"scene": null
				},
				{
					"id": -1,
					"name": "pages/index/index",
					"pathName": "pages/index/index",
					"query": "",
					"scene": null
				},
				{
					"id": -1,
					"name": "pages/designMode/designMode",
					"pathName": "pages/designMode/designMode",
					"query": "",
					"scene": null
				},
				{
					"id": -1,
					"name": "pages/finalize/finalize",
					"pathName": "pages/finalize/finalize",
					"query": "",
					"scene": null
				},
				{
					"id": -1,
					"name": "pages/detail/detail",
					"pathName": "pages/detail/detail",
					"query": "",
					"scene": null
				},
				{
					"id": -1,
					"name": "pages/finalize/finalize",
					"pathName": "pages/finalize/finalize",
					"query": "",
					"scene": null
				},
				{
					"id": -1,
					"name": "pages/share/share",
					"pathName": "pages/share/share",
					"query": "",
					"scene": null
				},
				{
					"id": -1,
					"name": "pages/index/index",
					"pathName": "pages/index/index",
					"query": "",
					"scene": null
				},
				{
					"id": -1,
					"name": "pages/wallet/wallet",
					"pathName": "pages/wallet/wallet",
					"query": "",
					"scene": null
				},
				{
					"id": -1,
					"name": "pages/comfirm/comfirm",
					"pathName": "pages/comfirm/comfirm",
					"query": "",
					"scene": null
				},
				{
					"id": -1,
					"name": "pages/design/design",
					"pathName": "pages/design/design",
					"scene": null
				}
			]
		}
	}
}